<?xml version="1.0" encoding="UTF-8"?>
<!DOCTYPE mapper PUBLIC "-//mybatis.org//DTD Mapper 3.0//EN" "http://mybatis.org/dtd/mybatis-3-mapper.dtd">
<mapper namespace="com.platform.dao.OfflineOrderInfoPoMapper">
  <resultMap id="BaseResultMap" type="com.platform.entity.OfflineOrderInfoPo">
    <!--
      WARNING - @mbggenerated
      This element is automatically generated by MyBatis Generator, do not modify.
      This element was generated on Mon Sep 23 10:05:23 CST 2019.
    -->
    <id column="id" jdbcType="INTEGER" property="id" />
    <result column="goods_id" jdbcType="INTEGER" property="goodsId" />
    <result column="order_no" jdbcType="VARCHAR" property="orderNo" />
    <result column="order_type" jdbcType="INTEGER" property="orderType" />
    <result column="order_status" jdbcType="INTEGER" property="orderStatus" />
    <result column="payment_status" jdbcType="INTEGER" property="paymentStatus" />
    <result column="payment_time" jdbcType="TIMESTAMP" property="paymentTime" />
    <result column="payment_no" jdbcType="VARCHAR" property="paymentNo" />
    <result column="payment_price" jdbcType="DECIMAL" property="paymentPrice" />
    <result column="order_price" jdbcType="DECIMAL" property="orderPrice" />
    <result column="service_house_name" jdbcType="VARCHAR" property="serviceHouseName" />
    <result column="service_time" jdbcType="VARCHAR" property="serviceTime" />
    <result column="service_required" jdbcType="VARCHAR" property="serviceRequired" />
    <result column="problem_description" jdbcType="VARCHAR" property="problemDescription" />
    <result column="service_type" jdbcType="VARCHAR" property="serviceType" />
    <result column="service_space" jdbcType="VARCHAR" property="serviceSpace" />
    <result column="service_acreage" jdbcType="VARCHAR" property="serviceAcreage" />
    <result column="service_idea" jdbcType="VARCHAR" property="serviceIdea" />
    <result column="service_air_conditioner_model" jdbcType="VARCHAR" property="serviceAirConditionerModel" />
    <result column="service_air_conditioner_type" jdbcType="VARCHAR" property="serviceAirConditionerType" />
    <result column="service_furniture" jdbcType="VARCHAR" property="serviceFurniture" />
    <result column="service_house_type" jdbcType="VARCHAR" property="serviceHouseType" />
    <result column="service_house_delivery_standards" jdbcType="VARCHAR" property="serviceHouseDeliveryStandards" />
    <result column="contact_name" jdbcType="VARCHAR" property="contactName" />
    <result column="contact_mobile" jdbcType="VARCHAR" property="contactMobile" />
    <result column="address" jdbcType="VARCHAR" property="address" />
    <result column="create_time" jdbcType="TIMESTAMP" property="createTime" />
    <result column="update_time" jdbcType="TIMESTAMP" property="updateTime" />
    <result column="create_user_id" jdbcType="BIGINT" property="createUserId" />
    <result column="update_user_id" jdbcType="BIGINT" property="updateUserId" />
    <result column="defunct" jdbcType="INTEGER" property="defunct" />
    <result column="coupon_id" jdbcType="INTEGER" property="couponId" />
    <result column="coupon_price" jdbcType="DECIMAL" property="couponPrice" />
    <result column="channel_id" jdbcType="INTEGER" property="channelId" />
    <result column="master_worker" jdbcType="VARCHAR" property="masterWorker" />
    <result column="master_worker_id" jdbcType="BIGINT" property="masterWorkerId" />
    <result column="is_outer_order" jdbcType="SMALLINT" property="isOuterOrder" />
    <result column="outer_merchant_name" jdbcType="VARCHAR" property="outerMerchantName" />
    <result column="outer_service_category" jdbcType="VARCHAR" property="outerServiceCategory" />
    <result column="outer_service_content" jdbcType="VARCHAR" property="outerServiceContent" />
    <result column="outer_service_brand" jdbcType="VARCHAR" property="outerServiceBrand" />
    <result column="outer_service_combo" jdbcType="VARCHAR" property="outerServiceCombo" />
    <result column="batch_no" jdbcType="VARCHAR" property="batchNo" />
    <result column="store_id" jdbcType="BIGINT" property="storeId"/>
    <result column="shroff_account_number" jdbcType="VARCHAR" property="shroffAccountNumber"/>
    <result column="pay_channel" jdbcType="VARCHAR" property="payChannel"/>
  </resultMap>
  <sql id="Example_Where_Clause">
    <!--
      WARNING - @mbggenerated
      This element is automatically generated by MyBatis Generator, do not modify.
      This element was generated on Mon Sep 23 10:05:23 CST 2019.
    -->
    <where>
      <foreach collection="oredCriteria" item="criteria" separator="or">
        <if test="criteria.valid">
          <trim prefix="(" prefixOverrides="and" suffix=")">
            <foreach collection="criteria.criteria" item="criterion">
              <choose>
                <when test="criterion.noValue">
                  and ${criterion.condition}
                </when>
                <when test="criterion.singleValue">
                  and ${criterion.condition} #{criterion.value}
                </when>
                <when test="criterion.betweenValue">
                  and ${criterion.condition} #{criterion.value} and #{criterion.secondValue}
                </when>
                <when test="criterion.listValue">
                  and ${criterion.condition}
                  <foreach close=")" collection="criterion.value" item="listItem" open="(" separator=",">
                    #{listItem}
                  </foreach>
                </when>
              </choose>
            </foreach>
          </trim>
        </if>
      </foreach>
    </where>
  </sql>
  <sql id="Update_By_Example_Where_Clause">
    <!--
      WARNING - @mbggenerated
      This element is automatically generated by MyBatis Generator, do not modify.
      This element was generated on Mon Sep 23 10:05:23 CST 2019.
    -->
    <where>
      <foreach collection="example.oredCriteria" item="criteria" separator="or">
        <if test="criteria.valid">
          <trim prefix="(" prefixOverrides="and" suffix=")">
            <foreach collection="criteria.criteria" item="criterion">
              <choose>
                <when test="criterion.noValue">
                  and ${criterion.condition}
                </when>
                <when test="criterion.singleValue">
                  and ${criterion.condition} #{criterion.value}
                </when>
                <when test="criterion.betweenValue">
                  and ${criterion.condition} #{criterion.value} and #{criterion.secondValue}
                </when>
                <when test="criterion.listValue">
                  and ${criterion.condition}
                  <foreach close=")" collection="criterion.value" item="listItem" open="(" separator=",">
                    #{listItem}
                  </foreach>
                </when>
              </choose>
            </foreach>
          </trim>
        </if>
      </foreach>
    </where>
  </sql>
  <sql id="Base_Column_List">
    <!--
      WARNING - @mbggenerated
      This element is automatically generated by MyBatis Generator, do not modify.
      This element was generated on Mon Sep 23 10:05:23 CST 2019.
    -->
    id, goods_id, order_no, order_type, order_status, payment_status, payment_time, payment_no, 
    payment_price, order_price, service_house_name, service_time, service_required, problem_description, 
    service_type, service_space, service_acreage, service_idea, service_air_conditioner_model, 
    service_air_conditioner_type, service_furniture, service_house_type, service_house_delivery_standards, 
    contact_name, contact_mobile, address, create_time, update_time, create_user_id, 
    update_user_id, defunct, coupon_id, coupon_price, channel_id, master_worker, master_worker_id, 
    is_outer_order, outer_merchant_name, outer_service_category, outer_service_content, 
    outer_service_brand, outer_service_combo, batch_no
  </sql>
  <select id="selectByExample" parameterType="com.platform.entity.OfflineOrderInfoPoExample" resultMap="BaseResultMap">
    <!--
      WARNING - @mbggenerated
      This element is automatically generated by MyBatis Generator, do not modify.
      This element was generated on Mon Sep 23 10:05:23 CST 2019.
    -->
    select
    <if test="distinct">
      distinct
    </if>
    <include refid="Base_Column_List" />
    from nideshop_offline_order_info
    <if test="_parameter != null">
      <include refid="Example_Where_Clause" />
    </if>
    <if test="orderByClause != null">
      order by ${orderByClause}
    </if>
    <if test="offset != null">
      limit ${offset}, ${pageSize}
    </if>
  </select>
  <select id="selectByPrimaryKey" parameterType="java.lang.Integer" resultMap="BaseResultMap">
    <!--
      WARNING - @mbggenerated
      This element is automatically generated by MyBatis Generator, do not modify.
      This element was generated on Mon Sep 23 10:05:23 CST 2019.
    -->
    select 
    <include refid="Base_Column_List" />
    from nideshop_offline_order_info
    where id = #{id,jdbcType=INTEGER}
  </select>
  <delete id="deleteByPrimaryKey" parameterType="java.lang.Integer">
    <!--
      WARNING - @mbggenerated
      This element is automatically generated by MyBatis Generator, do not modify.
      This element was generated on Mon Sep 23 10:05:23 CST 2019.
    -->
    delete from nideshop_offline_order_info
    where id = #{id,jdbcType=INTEGER}
  </delete>
  <delete id="deleteByExample" parameterType="com.platform.entity.OfflineOrderInfoPoExample">
    <!--
      WARNING - @mbggenerated
      This element is automatically generated by MyBatis Generator, do not modify.
      This element was generated on Mon Sep 23 10:05:23 CST 2019.
    -->
    delete from nideshop_offline_order_info
    <if test="_parameter != null">
      <include refid="Example_Where_Clause" />
    </if>
  </delete>
  <insert id="insert" parameterType="com.platform.entity.OfflineOrderInfoPo">
    <!--
      WARNING - @mbggenerated
      This element is automatically generated by MyBatis Generator, do not modify.
      This element was generated on Mon Sep 23 10:05:23 CST 2019.
    -->
    <selectKey keyProperty="id" order="AFTER" resultType="java.lang.Integer">
      SELECT LAST_INSERT_ID()
    </selectKey>
    insert into nideshop_offline_order_info (goods_id, order_no, order_type, 
      order_status, payment_status, payment_time, 
      payment_no, payment_price, order_price, 
      service_house_name, service_time, service_required, 
      problem_description, service_type, service_space, 
      service_acreage, service_idea, service_air_conditioner_model, 
      service_air_conditioner_type, service_furniture, 
      service_house_type, service_house_delivery_standards, 
      contact_name, contact_mobile, address, 
      create_time, update_time, create_user_id, 
      update_user_id, defunct, coupon_id, 
      coupon_price, channel_id, master_worker, 
      master_worker_id, is_outer_order, outer_merchant_name, 
      outer_service_category, outer_service_content, 
      outer_service_brand, outer_service_combo, batch_no
      )
    values (#{goodsId,jdbcType=INTEGER}, #{orderNo,jdbcType=VARCHAR}, #{orderType,jdbcType=INTEGER}, 
      #{orderStatus,jdbcType=INTEGER}, #{paymentStatus,jdbcType=INTEGER}, #{paymentTime,jdbcType=TIMESTAMP}, 
      #{paymentNo,jdbcType=VARCHAR}, #{paymentPrice,jdbcType=DECIMAL}, #{orderPrice,jdbcType=DECIMAL}, 
      #{serviceHouseName,jdbcType=VARCHAR}, #{serviceTime,jdbcType=VARCHAR}, #{serviceRequired,jdbcType=VARCHAR}, 
      #{problemDescription,jdbcType=VARCHAR}, #{serviceType,jdbcType=VARCHAR}, #{serviceSpace,jdbcType=VARCHAR}, 
      #{serviceAcreage,jdbcType=VARCHAR}, #{serviceIdea,jdbcType=VARCHAR}, #{serviceAirConditionerModel,jdbcType=VARCHAR}, 
      #{serviceAirConditionerType,jdbcType=VARCHAR}, #{serviceFurniture,jdbcType=VARCHAR}, 
      #{serviceHouseType,jdbcType=VARCHAR}, #{serviceHouseDeliveryStandards,jdbcType=VARCHAR}, 
      #{contactName,jdbcType=VARCHAR}, #{contactMobile,jdbcType=VARCHAR}, #{address,jdbcType=VARCHAR}, 
      #{createTime,jdbcType=TIMESTAMP}, #{updateTime,jdbcType=TIMESTAMP}, #{createUserId,jdbcType=BIGINT}, 
      #{updateUserId,jdbcType=BIGINT}, #{defunct,jdbcType=INTEGER}, #{couponId,jdbcType=INTEGER}, 
      #{couponPrice,jdbcType=DECIMAL}, #{channelId,jdbcType=INTEGER}, #{masterWorker,jdbcType=VARCHAR}, 
      #{masterWorkerId,jdbcType=BIGINT}, #{isOuterOrder,jdbcType=SMALLINT}, #{outerMerchantName,jdbcType=VARCHAR}, 
      #{outerServiceCategory,jdbcType=VARCHAR}, #{outerServiceContent,jdbcType=VARCHAR}, 
      #{outerServiceBrand,jdbcType=VARCHAR}, #{outerServiceCombo,jdbcType=VARCHAR}, #{batchNo,jdbcType=VARCHAR}
      )
  </insert>
  <insert id="insertSelective" parameterType="com.platform.entity.OfflineOrderInfoPo">
    <!--
      WARNING - @mbggenerated
      This element is automatically generated by MyBatis Generator, do not modify.
      This element was generated on Mon Sep 23 10:05:23 CST 2019.
    -->
    <selectKey keyProperty="id" order="AFTER" resultType="java.lang.Integer">
      SELECT LAST_INSERT_ID()
    </selectKey>
    insert into nideshop_offline_order_info
    <trim prefix="(" suffix=")" suffixOverrides=",">
      <if test="goodsId != null">
        goods_id,
      </if>
      <if test="orderNo != null">
        order_no,
      </if>
      <if test="orderType != null">
        order_type,
      </if>
      <if test="orderStatus != null">
        order_status,
      </if>
      <if test="paymentStatus != null">
        payment_status,
      </if>
      <if test="paymentTime != null">
        payment_time,
      </if>
      <if test="paymentNo != null">
        payment_no,
      </if>
      <if test="paymentPrice != null">
        payment_price,
      </if>
      <if test="orderPrice != null">
        order_price,
      </if>
      <if test="serviceHouseName != null">
        service_house_name,
      </if>
      <if test="serviceTime != null">
        service_time,
      </if>
      <if test="serviceRequired != null">
        service_required,
      </if>
      <if test="problemDescription != null">
        problem_description,
      </if>
      <if test="serviceType != null">
        service_type,
      </if>
      <if test="serviceSpace != null">
        service_space,
      </if>
      <if test="serviceAcreage != null">
        service_acreage,
      </if>
      <if test="serviceIdea != null">
        service_idea,
      </if>
      <if test="serviceAirConditionerModel != null">
        service_air_conditioner_model,
      </if>
      <if test="serviceAirConditionerType != null">
        service_air_conditioner_type,
      </if>
      <if test="serviceFurniture != null">
        service_furniture,
      </if>
      <if test="serviceHouseType != null">
        service_house_type,
      </if>
      <if test="serviceHouseDeliveryStandards != null">
        service_house_delivery_standards,
      </if>
      <if test="contactName != null">
        contact_name,
      </if>
      <if test="contactMobile != null">
        contact_mobile,
      </if>
      <if test="address != null">
        address,
      </if>
      <if test="createTime != null">
        create_time,
      </if>
      <if test="updateTime != null">
        update_time,
      </if>
      <if test="createUserId != null">
        create_user_id,
      </if>
      <if test="updateUserId != null">
        update_user_id,
      </if>
      <if test="defunct != null">
        defunct,
      </if>
      <if test="couponId != null">
        coupon_id,
      </if>
      <if test="couponPrice != null">
        coupon_price,
      </if>
      <if test="channelId != null">
        channel_id,
      </if>
      <if test="masterWorker != null">
        master_worker,
      </if>
      <if test="masterWorkerId != null">
        master_worker_id,
      </if>
      <if test="isOuterOrder != null">
        is_outer_order,
      </if>
      <if test="outerMerchantName != null">
        outer_merchant_name,
      </if>
      <if test="outerServiceCategory != null">
        outer_service_category,
      </if>
      <if test="outerServiceContent != null">
        outer_service_content,
      </if>
      <if test="outerServiceBrand != null">
        outer_service_brand,
      </if>
      <if test="outerServiceCombo != null">
        outer_service_combo,
      </if>
      <if test="batchNo != null">
        batch_no,
      </if>
    </trim>
    <trim prefix="values (" suffix=")" suffixOverrides=",">
      <if test="goodsId != null">
        #{goodsId,jdbcType=INTEGER},
      </if>
      <if test="orderNo != null">
        #{orderNo,jdbcType=VARCHAR},
      </if>
      <if test="orderType != null">
        #{orderType,jdbcType=INTEGER},
      </if>
      <if test="orderStatus != null">
        #{orderStatus,jdbcType=INTEGER},
      </if>
      <if test="paymentStatus != null">
        #{paymentStatus,jdbcType=INTEGER},
      </if>
      <if test="paymentTime != null">
        #{paymentTime,jdbcType=TIMESTAMP},
      </if>
      <if test="paymentNo != null">
        #{paymentNo,jdbcType=VARCHAR},
      </if>
      <if test="paymentPrice != null">
        #{paymentPrice,jdbcType=DECIMAL},
      </if>
      <if test="orderPrice != null">
        #{orderPrice,jdbcType=DECIMAL},
      </if>
      <if test="serviceHouseName != null">
        #{serviceHouseName,jdbcType=VARCHAR},
      </if>
      <if test="serviceTime != null">
        #{serviceTime,jdbcType=VARCHAR},
      </if>
      <if test="serviceRequired != null">
        #{serviceRequired,jdbcType=VARCHAR},
      </if>
      <if test="problemDescription != null">
        #{problemDescription,jdbcType=VARCHAR},
      </if>
      <if test="serviceType != null">
        #{serviceType,jdbcType=VARCHAR},
      </if>
      <if test="serviceSpace != null">
        #{serviceSpace,jdbcType=VARCHAR},
      </if>
      <if test="serviceAcreage != null">
        #{serviceAcreage,jdbcType=VARCHAR},
      </if>
      <if test="serviceIdea != null">
        #{serviceIdea,jdbcType=VARCHAR},
      </if>
      <if test="serviceAirConditionerModel != null">
        #{serviceAirConditionerModel,jdbcType=VARCHAR},
      </if>
      <if test="serviceAirConditionerType != null">
        #{serviceAirConditionerType,jdbcType=VARCHAR},
      </if>
      <if test="serviceFurniture != null">
        #{serviceFurniture,jdbcType=VARCHAR},
      </if>
      <if test="serviceHouseType != null">
        #{serviceHouseType,jdbcType=VARCHAR},
      </if>
      <if test="serviceHouseDeliveryStandards != null">
        #{serviceHouseDeliveryStandards,jdbcType=VARCHAR},
      </if>
      <if test="contactName != null">
        #{contactName,jdbcType=VARCHAR},
      </if>
      <if test="contactMobile != null">
        #{contactMobile,jdbcType=VARCHAR},
      </if>
      <if test="address != null">
        #{address,jdbcType=VARCHAR},
      </if>
      <if test="createTime != null">
        #{createTime,jdbcType=TIMESTAMP},
      </if>
      <if test="updateTime != null">
        #{updateTime,jdbcType=TIMESTAMP},
      </if>
      <if test="createUserId != null">
        #{createUserId,jdbcType=BIGINT},
      </if>
      <if test="updateUserId != null">
        #{updateUserId,jdbcType=BIGINT},
      </if>
      <if test="defunct != null">
        #{defunct,jdbcType=INTEGER},
      </if>
      <if test="couponId != null">
        #{couponId,jdbcType=INTEGER},
      </if>
      <if test="couponPrice != null">
        #{couponPrice,jdbcType=DECIMAL},
      </if>
      <if test="channelId != null">
        #{channelId,jdbcType=INTEGER},
      </if>
      <if test="masterWorker != null">
        #{masterWorker,jdbcType=VARCHAR},
      </if>
      <if test="masterWorkerId != null">
        #{masterWorkerId,jdbcType=BIGINT},
      </if>
      <if test="isOuterOrder != null">
        #{isOuterOrder,jdbcType=SMALLINT},
      </if>
      <if test="outerMerchantName != null">
        #{outerMerchantName,jdbcType=VARCHAR},
      </if>
      <if test="outerServiceCategory != null">
        #{outerServiceCategory,jdbcType=VARCHAR},
      </if>
      <if test="outerServiceContent != null">
        #{outerServiceContent,jdbcType=VARCHAR},
      </if>
      <if test="outerServiceBrand != null">
        #{outerServiceBrand,jdbcType=VARCHAR},
      </if>
      <if test="outerServiceCombo != null">
        #{outerServiceCombo,jdbcType=VARCHAR},
      </if>
      <if test="batchNo != null">
        #{batchNo,jdbcType=VARCHAR},
      </if>
    </trim>
  </insert>
  <select id="countByExample" parameterType="com.platform.entity.OfflineOrderInfoPoExample" resultType="java.lang.Integer">
    <!--
      WARNING - @mbggenerated
      This element is automatically generated by MyBatis Generator, do not modify.
      This element was generated on Mon Sep 23 10:05:23 CST 2019.
    -->
    select count(*) from nideshop_offline_order_info
    <if test="_parameter != null">
      <include refid="Example_Where_Clause" />
    </if>
  </select>
  <update id="updateByExampleSelective" parameterType="map">
    <!--
      WARNING - @mbggenerated
      This element is automatically generated by MyBatis Generator, do not modify.
      This element was generated on Mon Sep 23 10:05:23 CST 2019.
    -->
    update nideshop_offline_order_info
    <set>
      <if test="record.id != null">
        id = #{record.id,jdbcType=INTEGER},
      </if>
      <if test="record.goodsId != null">
        goods_id = #{record.goodsId,jdbcType=INTEGER},
      </if>
      <if test="record.orderNo != null">
        order_no = #{record.orderNo,jdbcType=VARCHAR},
      </if>
      <if test="record.orderType != null">
        order_type = #{record.orderType,jdbcType=INTEGER},
      </if>
      <if test="record.orderStatus != null">
        order_status = #{record.orderStatus,jdbcType=INTEGER},
      </if>
      <if test="record.paymentStatus != null">
        payment_status = #{record.paymentStatus,jdbcType=INTEGER},
      </if>
      <if test="record.paymentTime != null">
        payment_time = #{record.paymentTime,jdbcType=TIMESTAMP},
      </if>
      <if test="record.paymentNo != null">
        payment_no = #{record.paymentNo,jdbcType=VARCHAR},
      </if>
      <if test="record.paymentPrice != null">
        payment_price = #{record.paymentPrice,jdbcType=DECIMAL},
      </if>
      <if test="record.orderPrice != null">
        order_price = #{record.orderPrice,jdbcType=DECIMAL},
      </if>
      <if test="record.serviceHouseName != null">
        service_house_name = #{record.serviceHouseName,jdbcType=VARCHAR},
      </if>
      <if test="record.serviceTime != null">
        service_time = #{record.serviceTime,jdbcType=VARCHAR},
      </if>
      <if test="record.serviceRequired != null">
        service_required = #{record.serviceRequired,jdbcType=VARCHAR},
      </if>
      <if test="record.problemDescription != null">
        problem_description = #{record.problemDescription,jdbcType=VARCHAR},
      </if>
      <if test="record.serviceType != null">
        service_type = #{record.serviceType,jdbcType=VARCHAR},
      </if>
      <if test="record.serviceSpace != null">
        service_space = #{record.serviceSpace,jdbcType=VARCHAR},
      </if>
      <if test="record.serviceAcreage != null">
        service_acreage = #{record.serviceAcreage,jdbcType=VARCHAR},
      </if>
      <if test="record.serviceIdea != null">
        service_idea = #{record.serviceIdea,jdbcType=VARCHAR},
      </if>
      <if test="record.serviceAirConditionerModel != null">
        service_air_conditioner_model = #{record.serviceAirConditionerModel,jdbcType=VARCHAR},
      </if>
      <if test="record.serviceAirConditionerType != null">
        service_air_conditioner_type = #{record.serviceAirConditionerType,jdbcType=VARCHAR},
      </if>
      <if test="record.serviceFurniture != null">
        service_furniture = #{record.serviceFurniture,jdbcType=VARCHAR},
      </if>
      <if test="record.serviceHouseType != null">
        service_house_type = #{record.serviceHouseType,jdbcType=VARCHAR},
      </if>
      <if test="record.serviceHouseDeliveryStandards != null">
        service_house_delivery_standards = #{record.serviceHouseDeliveryStandards,jdbcType=VARCHAR},
      </if>
      <if test="record.contactName != null">
        contact_name = #{record.contactName,jdbcType=VARCHAR},
      </if>
      <if test="record.contactMobile != null">
        contact_mobile = #{record.contactMobile,jdbcType=VARCHAR},
      </if>
      <if test="record.address != null">
        address = #{record.address,jdbcType=VARCHAR},
      </if>
      <if test="record.createTime != null">
        create_time = #{record.createTime,jdbcType=TIMESTAMP},
      </if>
      <if test="record.updateTime != null">
        update_time = #{record.updateTime,jdbcType=TIMESTAMP},
      </if>
      <if test="record.createUserId != null">
        create_user_id = #{record.createUserId,jdbcType=BIGINT},
      </if>
      <if test="record.updateUserId != null">
        update_user_id = #{record.updateUserId,jdbcType=BIGINT},
      </if>
      <if test="record.defunct != null">
        defunct = #{record.defunct,jdbcType=INTEGER},
      </if>
      <if test="record.couponId != null">
        coupon_id = #{record.couponId,jdbcType=INTEGER},
      </if>
      <if test="record.couponPrice != null">
        coupon_price = #{record.couponPrice,jdbcType=DECIMAL},
      </if>
      <if test="record.channelId != null">
        channel_id = #{record.channelId,jdbcType=INTEGER},
      </if>
      <if test="record.masterWorker != null">
        master_worker = #{record.masterWorker,jdbcType=VARCHAR},
      </if>
      <if test="record.masterWorkerId != null">
        master_worker_id = #{record.masterWorkerId,jdbcType=BIGINT},
      </if>
      <if test="record.isOuterOrder != null">
        is_outer_order = #{record.isOuterOrder,jdbcType=SMALLINT},
      </if>
      <if test="record.outerMerchantName != null">
        outer_merchant_name = #{record.outerMerchantName,jdbcType=VARCHAR},
      </if>
      <if test="record.outerServiceCategory != null">
        outer_service_category = #{record.outerServiceCategory,jdbcType=VARCHAR},
      </if>
      <if test="record.outerServiceContent != null">
        outer_service_content = #{record.outerServiceContent,jdbcType=VARCHAR},
      </if>
      <if test="record.outerServiceBrand != null">
        outer_service_brand = #{record.outerServiceBrand,jdbcType=VARCHAR},
      </if>
      <if test="record.outerServiceCombo != null">
        outer_service_combo = #{record.outerServiceCombo,jdbcType=VARCHAR},
      </if>
      <if test="record.batchNo != null">
        batch_no = #{record.batchNo,jdbcType=VARCHAR},
      </if>
    </set>
    <if test="_parameter != null">
      <include refid="Update_By_Example_Where_Clause" />
    </if>
  </update>
  <update id="updateByExample" parameterType="map">
    <!--
      WARNING - @mbggenerated
      This element is automatically generated by MyBatis Generator, do not modify.
      This element was generated on Mon Sep 23 10:05:23 CST 2019.
    -->
    update nideshop_offline_order_info
    set id = #{record.id,jdbcType=INTEGER},
      goods_id = #{record.goodsId,jdbcType=INTEGER},
      order_no = #{record.orderNo,jdbcType=VARCHAR},
      order_type = #{record.orderType,jdbcType=INTEGER},
      order_status = #{record.orderStatus,jdbcType=INTEGER},
      payment_status = #{record.paymentStatus,jdbcType=INTEGER},
      payment_time = #{record.paymentTime,jdbcType=TIMESTAMP},
      payment_no = #{record.paymentNo,jdbcType=VARCHAR},
      payment_price = #{record.paymentPrice,jdbcType=DECIMAL},
      order_price = #{record.orderPrice,jdbcType=DECIMAL},
      service_house_name = #{record.serviceHouseName,jdbcType=VARCHAR},
      service_time = #{record.serviceTime,jdbcType=VARCHAR},
      service_required = #{record.serviceRequired,jdbcType=VARCHAR},
      problem_description = #{record.problemDescription,jdbcType=VARCHAR},
      service_type = #{record.serviceType,jdbcType=VARCHAR},
      service_space = #{record.serviceSpace,jdbcType=VARCHAR},
      service_acreage = #{record.serviceAcreage,jdbcType=VARCHAR},
      service_idea = #{record.serviceIdea,jdbcType=VARCHAR},
      service_air_conditioner_model = #{record.serviceAirConditionerModel,jdbcType=VARCHAR},
      service_air_conditioner_type = #{record.serviceAirConditionerType,jdbcType=VARCHAR},
      service_furniture = #{record.serviceFurniture,jdbcType=VARCHAR},
      service_house_type = #{record.serviceHouseType,jdbcType=VARCHAR},
      service_house_delivery_standards = #{record.serviceHouseDeliveryStandards,jdbcType=VARCHAR},
      contact_name = #{record.contactName,jdbcType=VARCHAR},
      contact_mobile = #{record.contactMobile,jdbcType=VARCHAR},
      address = #{record.address,jdbcType=VARCHAR},
      create_time = #{record.createTime,jdbcType=TIMESTAMP},
      update_time = #{record.updateTime,jdbcType=TIMESTAMP},
      create_user_id = #{record.createUserId,jdbcType=BIGINT},
      update_user_id = #{record.updateUserId,jdbcType=BIGINT},
      defunct = #{record.defunct,jdbcType=INTEGER},
      coupon_id = #{record.couponId,jdbcType=INTEGER},
      coupon_price = #{record.couponPrice,jdbcType=DECIMAL},
      channel_id = #{record.channelId,jdbcType=INTEGER},
      master_worker = #{record.masterWorker,jdbcType=VARCHAR},
      master_worker_id = #{record.masterWorkerId,jdbcType=BIGINT},
      is_outer_order = #{record.isOuterOrder,jdbcType=SMALLINT},
      outer_merchant_name = #{record.outerMerchantName,jdbcType=VARCHAR},
      outer_service_category = #{record.outerServiceCategory,jdbcType=VARCHAR},
      outer_service_content = #{record.outerServiceContent,jdbcType=VARCHAR},
      outer_service_brand = #{record.outerServiceBrand,jdbcType=VARCHAR},
      outer_service_combo = #{record.outerServiceCombo,jdbcType=VARCHAR},
      batch_no = #{record.batchNo,jdbcType=VARCHAR}
    <if test="_parameter != null">
      <include refid="Update_By_Example_Where_Clause" />
    </if>
  </update>
  <update id="updateByPrimaryKeySelective" parameterType="com.platform.entity.OfflineOrderInfoPo">
    <!--
      WARNING - @mbggenerated
      This element is automatically generated by MyBatis Generator, do not modify.
      This element was generated on Mon Sep 23 10:05:23 CST 2019.
    -->
    update nideshop_offline_order_info
    <set>
      <if test="goodsId != null">
        goods_id = #{goodsId,jdbcType=INTEGER},
      </if>
      <if test="orderNo != null">
        order_no = #{orderNo,jdbcType=VARCHAR},
      </if>
      <if test="orderType != null">
        order_type = #{orderType,jdbcType=INTEGER},
      </if>
      <if test="orderStatus != null">
        order_status = #{orderStatus,jdbcType=INTEGER},
      </if>
      <if test="paymentStatus != null">
        payment_status = #{paymentStatus,jdbcType=INTEGER},
      </if>
      <if test="paymentTime != null">
        payment_time = #{paymentTime,jdbcType=TIMESTAMP},
      </if>
      <if test="paymentNo != null">
        payment_no = #{paymentNo,jdbcType=VARCHAR},
      </if>
      <if test="paymentPrice != null">
        payment_price = #{paymentPrice,jdbcType=DECIMAL},
      </if>
      <if test="orderPrice != null">
        order_price = #{orderPrice,jdbcType=DECIMAL},
      </if>
      <if test="serviceHouseName != null">
        service_house_name = #{serviceHouseName,jdbcType=VARCHAR},
      </if>
      <if test="serviceTime != null">
        service_time = #{serviceTime,jdbcType=VARCHAR},
      </if>
      <if test="serviceRequired != null">
        service_required = #{serviceRequired,jdbcType=VARCHAR},
      </if>
      <if test="problemDescription != null">
        problem_description = #{problemDescription,jdbcType=VARCHAR},
      </if>
      <if test="serviceType != null">
        service_type = #{serviceType,jdbcType=VARCHAR},
      </if>
      <if test="serviceSpace != null">
        service_space = #{serviceSpace,jdbcType=VARCHAR},
      </if>
      <if test="serviceAcreage != null">
        service_acreage = #{serviceAcreage,jdbcType=VARCHAR},
      </if>
      <if test="serviceIdea != null">
        service_idea = #{serviceIdea,jdbcType=VARCHAR},
      </if>
      <if test="serviceAirConditionerModel != null">
        service_air_conditioner_model = #{serviceAirConditionerModel,jdbcType=VARCHAR},
      </if>
      <if test="serviceAirConditionerType != null">
        service_air_conditioner_type = #{serviceAirConditionerType,jdbcType=VARCHAR},
      </if>
      <if test="serviceFurniture != null">
        service_furniture = #{serviceFurniture,jdbcType=VARCHAR},
      </if>
      <if test="serviceHouseType != null">
        service_house_type = #{serviceHouseType,jdbcType=VARCHAR},
      </if>
      <if test="serviceHouseDeliveryStandards != null">
        service_house_delivery_standards = #{serviceHouseDeliveryStandards,jdbcType=VARCHAR},
      </if>
      <if test="contactName != null">
        contact_name = #{contactName,jdbcType=VARCHAR},
      </if>
      <if test="contactMobile != null">
        contact_mobile = #{contactMobile,jdbcType=VARCHAR},
      </if>
      <if test="address != null">
        address = #{address,jdbcType=VARCHAR},
      </if>
      <if test="createTime != null">
        create_time = #{createTime,jdbcType=TIMESTAMP},
      </if>
      <if test="updateTime != null">
        update_time = #{updateTime,jdbcType=TIMESTAMP},
      </if>
      <if test="createUserId != null">
        create_user_id = #{createUserId,jdbcType=BIGINT},
      </if>
      <if test="updateUserId != null">
        update_user_id = #{updateUserId,jdbcType=BIGINT},
      </if>
      <if test="defunct != null">
        defunct = #{defunct,jdbcType=INTEGER},
      </if>
      <if test="couponId != null">
        coupon_id = #{couponId,jdbcType=INTEGER},
      </if>
      <if test="couponPrice != null">
        coupon_price = #{couponPrice,jdbcType=DECIMAL},
      </if>
      <if test="channelId != null">
        channel_id = #{channelId,jdbcType=INTEGER},
      </if>
      <if test="masterWorker != null">
        master_worker = #{masterWorker,jdbcType=VARCHAR},
      </if>
      <if test="masterWorkerId != null">
        master_worker_id = #{masterWorkerId,jdbcType=BIGINT},
      </if>
      <if test="isOuterOrder != null">
        is_outer_order = #{isOuterOrder,jdbcType=SMALLINT},
      </if>
      <if test="outerMerchantName != null">
        outer_merchant_name = #{outerMerchantName,jdbcType=VARCHAR},
      </if>
      <if test="outerServiceCategory != null">
        outer_service_category = #{outerServiceCategory,jdbcType=VARCHAR},
      </if>
      <if test="outerServiceContent != null">
        outer_service_content = #{outerServiceContent,jdbcType=VARCHAR},
      </if>
      <if test="outerServiceBrand != null">
        outer_service_brand = #{outerServiceBrand,jdbcType=VARCHAR},
      </if>
      <if test="outerServiceCombo != null">
        outer_service_combo = #{outerServiceCombo,jdbcType=VARCHAR},
      </if>
      <if test="batchNo != null">
        batch_no = #{batchNo,jdbcType=VARCHAR},
      </if>
    </set>
    where id = #{id,jdbcType=INTEGER}
  </update>
  <update id="updateByPrimaryKey" parameterType="com.platform.entity.OfflineOrderInfoPo">
    <!--
      WARNING - @mbggenerated
      This element is automatically generated by MyBatis Generator, do not modify.
      This element was generated on Mon Sep 23 10:05:23 CST 2019.
    -->
    update nideshop_offline_order_info
    set goods_id = #{goodsId,jdbcType=INTEGER},
      order_no = #{orderNo,jdbcType=VARCHAR},
      order_type = #{orderType,jdbcType=INTEGER},
      order_status = #{orderStatus,jdbcType=INTEGER},
      payment_status = #{paymentStatus,jdbcType=INTEGER},
      payment_time = #{paymentTime,jdbcType=TIMESTAMP},
      payment_no = #{paymentNo,jdbcType=VARCHAR},
      payment_price = #{paymentPrice,jdbcType=DECIMAL},
      order_price = #{orderPrice,jdbcType=DECIMAL},
      service_house_name = #{serviceHouseName,jdbcType=VARCHAR},
      service_time = #{serviceTime,jdbcType=VARCHAR},
      service_required = #{serviceRequired,jdbcType=VARCHAR},
      problem_description = #{problemDescription,jdbcType=VARCHAR},
      service_type = #{serviceType,jdbcType=VARCHAR},
      service_space = #{serviceSpace,jdbcType=VARCHAR},
      service_acreage = #{serviceAcreage,jdbcType=VARCHAR},
      service_idea = #{serviceIdea,jdbcType=VARCHAR},
      service_air_conditioner_model = #{serviceAirConditionerModel,jdbcType=VARCHAR},
      service_air_conditioner_type = #{serviceAirConditionerType,jdbcType=VARCHAR},
      service_furniture = #{serviceFurniture,jdbcType=VARCHAR},
      service_house_type = #{serviceHouseType,jdbcType=VARCHAR},
      service_house_delivery_standards = #{serviceHouseDeliveryStandards,jdbcType=VARCHAR},
      contact_name = #{contactName,jdbcType=VARCHAR},
      contact_mobile = #{contactMobile,jdbcType=VARCHAR},
      address = #{address,jdbcType=VARCHAR},
      create_time = #{createTime,jdbcType=TIMESTAMP},
      update_time = #{updateTime,jdbcType=TIMESTAMP},
      create_user_id = #{createUserId,jdbcType=BIGINT},
      update_user_id = #{updateUserId,jdbcType=BIGINT},
      defunct = #{defunct,jdbcType=INTEGER},
      coupon_id = #{couponId,jdbcType=INTEGER},
      coupon_price = #{couponPrice,jdbcType=DECIMAL},
      channel_id = #{channelId,jdbcType=INTEGER},
      master_worker = #{masterWorker,jdbcType=VARCHAR},
      master_worker_id = #{masterWorkerId,jdbcType=BIGINT},
      is_outer_order = #{isOuterOrder,jdbcType=SMALLINT},
      outer_merchant_name = #{outerMerchantName,jdbcType=VARCHAR},
      outer_service_category = #{outerServiceCategory,jdbcType=VARCHAR},
      outer_service_content = #{outerServiceContent,jdbcType=VARCHAR},
      outer_service_brand = #{outerServiceBrand,jdbcType=VARCHAR},
      outer_service_combo = #{outerServiceCombo,jdbcType=VARCHAR},
      batch_no = #{batchNo,jdbcType=VARCHAR}
    where id = #{id,jdbcType=INTEGER}
  </update>

  <select id="queryListByMap" resultType="com.platform.entity.OfflineOrderInfoPo">
    select o.*,u.username as userName,u.mobile as userMobile,
    nc.name as channelName,sc.name as storeName,sc.address as storeAddress,sc.contact as storeContact
    from nideshop_offline_order_info o
    left join nideshop_user u on o.create_user_id = u.id
    left join nideshop_channel nc on nc.id=o.channel_id
    left join sys_store sc on sc.store_id=o.store_id
    WHERE 1=1
    <if test="orderNo != null and orderNo.trim() != ''">
      AND o.order_no LIKE concat('%',#{orderNo},'%')
    </if>
    <if test="paymentstatus != null and paymentstatus.trim() != ''">
      AND o.payment_status = #{paymentstatus}
    </if>
    <if test="orderStatus != null and orderStatus.trim() != ''">
      AND o.order_status = #{orderStatus}
    </if>
    <if test="storeId != null and storeId.trim() != ''">
      AND o.store_id = #{storeId}
    </if>
    <if test="orderType != null and orderType.trim() != ''">
      AND o.order_type = #{orderType}
    </if>
    <if test="channelId != null and channelId.trim() != ''">
      and channel_id &gt;= #{channelId }
    </if>
    <if test="masterWorker != null and masterWorker.trim() != ''">
      and master_worker &lt; #{masterWorker }
    </if>
    <if test="startTime != null and startTime.trim() != ''">
      and payment_time &gt;= #{startTime }
    </if>
    <if test="endTime != null and endTime.trim() != ''">
      and payment_time &lt; #{endTime }
    </if>
        order by id asc
    <if test="offset != null and limit != null and limit != 0">
      limit #{offset}, #{limit}
    </if>
  </select>
</mapper>